datachart/__init__.py
datachart/constants.py
datachart/typings.py
datachart/charts/__init__.py
datachart/charts/bar_chart.py
datachart/charts/box_plot.py
datachart/charts/heatmap.py
datachart/charts/histogram.py
datachart/charts/line_chart.py
datachart/charts/parallel_coords.py
datachart/charts/scatter_chart.py
datachart/config/__init__.py
datachart/config/charts.py
datachart/config/configuration.py
datachart/themes/__init__.py
datachart/themes/default.py
datachart/themes/grayscale.py
datachart/themes/publication.py
datachart/utils/__init__.py
datachart/utils/figure.py
datachart/utils/stats.py
datachart/utils/_internal/__init__.py
datachart/utils/_internal/chart_builder.py
datachart/utils/_internal/colors.py
datachart/utils/_internal/config_helpers.py
datachart/utils/_internal/plot_engine.py
datachart-0.7.3.dist-info/licenses/LICENSE
datachart-0.7.3.dist-info/METADATA
datachart-0.7.3.dist-info/WHEEL
datachart-0.7.3.dist-info/top_level.txt
datachart-0.7.3.dist-info/RECORD
