Metadata-Version: 2.4
Name: datachart
Version: 0.7.3
Summary: The customizable data chart creation package
Author: Erik Novak
Maintainer: Erik Novak
License: BSD 3-Clause License
Project-URL: Source, https://github.com/eriknovak/datachart
Project-URL: Docs, https://github.com/eriknovak/datachart
Keywords: python,dataviz,visualization
Classifier: Intended Audience :: Science/Research
Classifier: Programming Language :: Python :: 3.10
Classifier: Programming Language :: Python :: 3.11
Classifier: Programming Language :: Python :: 3.12
Classifier: Programming Language :: Python :: 3.13
Classifier: License :: OSI Approved :: BSD License
Classifier: Operating System :: OS Independent
Classifier: Topic :: Scientific/Engineering :: Visualization
Classifier: Topic :: Multimedia :: Graphics
Classifier: Framework :: Matplotlib
Requires-Python: >=3.10
License-File: LICENSE
Requires-Dist: numpy
Requires-Dist: matplotlib
Requires-Dist: pypalettes
Requires-Dist: scipy
Provides-Extra: dev
Requires-Dist: black; extra == "dev"
Requires-Dist: flake8; extra == "dev"
Requires-Dist: python-githooks; extra == "dev"
Requires-Dist: mkdocs-material; extra == "dev"
Requires-Dist: mkdocs-jupyter; extra == "dev"
Requires-Dist: mkdocstrings[python]; extra == "dev"
Provides-Extra: test
Requires-Dist: coverage; extra == "test"
Requires-Dist: nbmake; extra == "test"
Provides-Extra: all
Requires-Dist: datachart[dev,test]; extra == "all"
Dynamic: license-file
